{
  "users": {
    "admin-1": {
      "id": "admin-1",
      "username": "admin",
      "email": "admin@gmail.com",
      "phoneNumber": "1234567890",
      "gender": "male",
      "passwordHash": "$2b$12$tKWButgX9CS6/4jx1BFkPOuXG5EGeIjOrOPK735gtY/qaZgwepXje",
      "isAdmin": true,
      "createdAt": "2025-10-12T05:29:59.127Z"
    },
    "c96jptt0ont": {
      "username": "test",
      "email": "test@gmail.com",
      "phoneNumber": "4356787634",
      "gender": "male",
      "passwordHash": "$2b$12$lFdR/lnSCbv.8FePBPLA/.RQwFv261BYQvr.n.JilR3wCTJ1C6bMC",
      "isAdmin": false,
      "id": "c96jptt0ont",
      "createdAt": "2025-10-12T05:33:32.864Z"
    }
  },
  "sessions": {
    "jhhk4qedbrmgn9v1oj": {
      "token": "jhhk4qedbrmgn9v1oj",
      "userId": "c96jptt0ont",
      "createdAt": 1760247414595
    }
  },
  "lastSaved": "2025-10-12T05:46:33.463Z"
}